ask_llm/__init__.py
ask_llm/decorators.py
ask_llm/images.py
ask_llm/utils.py
ask_llm-0.1.183.dist-info/LICENSE
ask_llm-0.1.183.dist-info/METADATA
ask_llm-0.1.183.dist-info/WHEEL
ask_llm-0.1.183.dist-info/top_level.txt
ask_llm-0.1.183.dist-info/RECORD
