Metadata-Version: 2.1
Name: ask-llm
Version: 0.1.183
Summary: The easiest way to supercharge your apps with LLM!
Home-page: https://github.com/FlorianMgs/ask-llm
Author: Florian Magisson
Author-email: madgic.shrooms@gmail.com
License: MIT
License-File: LICENSE
Requires-Dist: Jinja2 >=3.1.3
Requires-Dist: pillow >=10.2.0
Requires-Dist: langchain >=0.3.2
Requires-Dist: langchain-community >=0.3.1
Requires-Dist: langchain-core >=0.3.9
Requires-Dist: langchain-openai >=0.2.0
Requires-Dist: langchain-anthropic >=0.2.3
Requires-Dist: python-dotenv >=1.0.1
